{
	"id": 52955167,
	"name": "Deimos (EndLevel)",
	"tags": [
		"2.1",
		"XL",
		"Timings",
		"Precision",
		"Overall"
	],
	"author": 9848660956,
	"creators": [
		9848660956,
		7674540021,
		8290580637,
		8207695111,
		8619093026,
		3573652073,
		3499959060,
		1039017987,
		1944819447,
		9083661991,
		5786510864,
		4796048557,
		2394329204,
		3553811491
	],
	"verifier": 5106999290,
	"verification": "https://www.youtube.com/watch?v=FgxsNzQnF5o",
	"percentToQualify": 100,
	"password": "789123",
	"song": 436814,
	"records": [
		{
			"user": 5362479182,
			"link": "https://youtu.be/9b3j_DjxqNQ",
			"percent": 100,
			"hz": 360
		},
		{
			"user": 1150134972,
			"link": "https://www.youtube.com/watch?v=qvnWxPQmpNk&ab_channel=woi",
			"percent": 100,
			"hz": 300
		},
		{
			"user": 9306619221,
			"link": "https://www.youtube.com/watch?v=5V1uzl5DXdM",
			"percent": 100,
			"hz": 360
		},
		{
			"user": 9349980438,
			"link": "https://www.youtube.com/watch?v=t--_YEV4mZ4",
			"percent": 100,
			"hz": 360
		},
		{
			"user": 5987267239,
			"link": "https://www.youtube.com/watch?v=jGdyvqjgd0I&list=PLPCK6UQaU-5PWcqGYQIaUO9HCoFosGFOs&index=47",
			"percent": 100,
			"hz": 288
		},
		{
			"user": 9789402666,
			"link": "https://youtu.be/OFGfPT0QMg8",
			"percent": 100,
			"hz": 480
		},
		{
			"user": 7775567977,
			"link": "https://www.youtube.com/watch?v=ocQb2UBlRaU",
			"percent": 100,
			"hz": 360
		},
		{
			"user": 1032789438,
			"link": "https://www.youtube.com/watch?v=XcJFJbGXMsg",
			"percent": 100,
			"hz": 360
		},
		{
			"user": 7823877256,
			"link": "https://youtu.be/dYzfE81YHSs?si=mdaFgX-j-giXpDpD",
			"percent": 100,
			"hz": 360
		},
		{
			"user": 5392037032,
			"link": "https://youtu.be/xsCdH0S_5CI",
			"percent": 100,
			"hz": 360
		},
		{
			"user": 5601071722,
			"link": "https://youtu.be/iiYdEIl04gs",
			"percent": 100,
			"hz": 360
		},
		{
			"user": 5898278434,
			"link": "https://www.youtube.com/watch?v=4dD8cx7BB6Q",
			"percent": 100,
			"hz": 360
		},
		{
			"user": 6600555703,
			"link": "https://www.youtube.com/watch?v=3K9r5MSgTeE",
			"percent": 100,
			"hz": 360
		},
		{
			"user": 5011629074,
			"link": "https://youtu.be/MBPSYVpPjNA?si=uByKXi3EDfvIAi8r",
			"percent": 100,
			"hz": 360
		},
		{
			"user": 5622041352,
			"link": "https://www.youtube.com/watch?v=z6oJlzd6rK8",
			"percent": 100,
			"hz": 360
		},
		{
			"user": 7937190301,
			"link": "https://www.youtube.com/watch?v=PNhCb_Ucgyk",
			"percent": 100,
			"hz": 360
		}
	]
}