{
	"id": 57084298,
	"name": "Insaction",
	"author": "ByBoy 11",
	"creators": [
		"Axdrel",
		"Laser10",
		"Diplow",
		"Zafkiel",
		"ByBoy 11",
		"Chi",
		"Enboy",
		"M3llo",
		"Dro3",
		"Azos11",
		"Chuchitodomin",
		"NVATIUM",
		"Aqours",
		"JaxtilanX",
		"xanN",
		"ZadoxxZ",
		"icotchy",
		"DanielDLC",
		"Abdula",
		"TheBoringBoy",
		"Zyplex",
		"Lucalry",
		"Mapex",
		"DangerKat",
		"Gathitho",
		"IPersuit",
		"Trudee Fabian",
		"Blasting Ant",
		"ItzStrill",
		"Slip Ghost",
		"llJoanll",
		"Stamina"
	],
	"verifier": "Bibox",
	"verification": "https://youtu.be/vfvadYEj_k0",
	"percentToQualify": 100,
	"password": "282019",
	"records": [
		{
			"user": "SEDTHEPRODIGY",
			"link": "https://youtu.be/QL7CQXhAvw0",
			"percent": 100,
			"hz": 240
		},
		{
			"user": "Zenta",
			"link": "https://www.youtube.com/watch?v=9JdyFJrOHZo",
			"percent": 100,
			"hz": 360
		},
		{
			"user": "mrperson",
			"link": "https://youtu.be/_OKi3YcRDkQ",
			"percent": 100,
			"hz": 144
		},
		{
			"user": "Lia",
			"link": "https://youtu.be/kMqzcxuwanY",
			"percent": 100,
			"hz": 360
		},
		{
			"user": "Bleamer",
			"link": "https://www.youtube.com/watch?v=GCbkUBXAPzU&ab_channel=Bleamer",
			"percent": 100,
			"hz": 300
		},
		{
			"user": "thetitanking999",
			"link": "https://www.youtube.com/watch?v=GZnQPHGTYm0&t=2s",
			"percent": 100,
			"hz": 360
		},
		{
			"user": "Patrick61804",
			"link": "https://youtu.be/Hl66E0GZgXw",
			"percent": 100,
			"hz": 360
		},
		{
			"user": "LinedriveGD",
			"link": "https://www.youtube.com/watch?v=gXshGMS7kSc",
			"percent": 100,
			"hz": 300
		},
		{
			"user": "DartHole",
			"link": "https://youtu.be/hqCI9SJPTTE",
			"percent": 100,
			"hz": 144
		},
		{
			"user": "LuckyNS",
			"link": "https://youtu.be/V7fYBySIO0E",
			"percent": 100,
			"hz": 60
		},
		{
			"user": "NiceCrunchy",
			"link": "https://www.youtube.com/watch?v=R1ngXeNK7r8&t=2s",
			"percent": 100,
			"hz": 360
		},
		{
			"user": "ASBCHazel",
			"link": "https://www.youtube.com/watch?v=zxVT0_3IyUo",
			"percent": 100,
			"hz": 360
		},
		{
			"user": "HotNooB",
			"link": "https://youtu.be/_eb4KMzgBh4",
			"percent": 100,
			"hz": 288
		},
		{
			"user": "plimbus",
			"link": "https://youtu.be/TrIIeeB23no",
			"percent": 100,
			"hz": 360
		},
		{
			"user": "drigeordraig",
			"link": "https://youtu.be/Egcv4Mmyibw",
			"percent": 100,
			"hz": 330
		},
		{
			"user": "Alex_",
			"link": "https://youtu.be/g24P5Q1zSGw",
			"percent": 100,
			"hz": 360
		},
		{
			"user": "HamsterPlayz",
			"link": "https://youtu.be/D5Fc8TbhYgg",
			"percent": 100,
			"hz": 144
		},
		{
			"user": "ultrakawaHD",
			"link": "https://www.youtube.com/watch?v=8WF4vyjm218",
			"percent": 100,
			"hz": 360
		},
		{
			"user": "Ranly",
			"link": "https://youtu.be/u1Esa7Fc0KY",
			"percent": 100,
			"hz": 144
		},
		{
			"user": "TH54",
			"link": "https://youtu.be/1E7-JZ6F2LQ",
			"percent": 100,
			"hz": 360
		},
		{
			"user": "MeowMasterer",
			"link": "https://youtu.be/cBvua7pSPZU",
			"percent": 100,
			"hz": 75
		},
		{
			"user": "iRaily",
			"link": "https://youtu.be/4je6fOyH3-s?si=jnMIa7rrNxlPHagP",
			"percent": 100,
			"hz": 288
		},
		{
			"user": "BlueTomcat",
			"link": "https://youtu.be/G0kNwbGmNUI?si=29_GInnVcKcG-zRM",
			"percent": 100,
			"hz": 288
		},
		{
			"user": "Toxic507",
			"link": "https://youtu.be/uGwORldCLQ4?si=UfzQhQe60zGKFa_H",
			"percent": 100,
			"hz": 240
		},
		{
			"user": "ItzzElijah",
			"link": "https://www.youtube.com/watch?v=lKef8xOTwnA&t=52s",
			"percent": 100,
			"hz": 240
		},
		{
			"user": "AlexDIRO",
			"link": "https://www.youtube.com/watch?v=iB8AGmxiR44&list=PL5O1xXESiIKj2PIhyQXIc85tW80R1CNJU&index=28",
			"percent": 100,
			"hz": 144
		},
		{
			"user": "[JSL] zBlueBerry",
			"link": "https://youtu.be/jlnz6727P-Q?si=K8bWSeLQF1bcy9JA",
			"percent": 100,
			"hz": 360
		},
		{
			"user": "Zaforus305",
			"link": "https://youtu.be/opwnwwXKbt8",
			"percent": 100,
			"hz": 360
		},
		{
			"user": "Candy",
			"link": "https://youtu.be/qCzhRhqc5J8",
			"percent": 100,
			"hz": 360
		},
		{
			"user": "CarlaVeloso35P",
			"link": "https://youtu.be/Gtd5fl7NxHE?si=OvJmIL2zb5B6R7bS",
			"percent": 100,
			"hz": 360
		},
		{
			"user": "ItzFestr",
			"link": "https://www.youtube.com/watch?v=MXnozIv3orQ",
			"percent": 100,
			"hz": 360
		},
		{
			"user": "gr8ness",
			"link": "https://youtu.be/wc2PcmO5QYw?si=uVJImx3E0A5tx8MH",
			"percent": 100,
			"hz": 360
		},
		{
			"user": "ninezz",
			"link": "https://youtu.be/VsvOdg3nr-0?si=-CEYBX_N3h0Ci8B7",
			"percent": 100,
			"hz": 360
		},
		{
			"user": "Leslie",
			"link": "https://www.youtube.com/watch?v=tOEfHrvKuMs",
			"percent": 100,
			"hz": 360
		},
		{
			"user": "XDMNQ",
			"link": "https://youtu.be/NDqRxXqc3Q4?si=_fEs2wxLCb9C9YYr",
			"percent": 100,
			"hz": 360
		},
		{
			"user": "awesomeme360",
			"link": "https://youtu.be/0pHr-_GWb8g?si=6UZn-vB13OYUSbFN",
			"percent": 100,
			"hz": 360
		},
		{
			"user": "kas ia",
			"link": "https://youtu.be/hTEOWW4RV38?si=T35GdYe2qtycrxCy",
			"percent": 100,
			"hz": 360
		},
		{
			"user": "Ryclix",
			"link": "https://www.youtube.com/watch?v=jd8ZPT8QDzU",
			"percent": 100,
			"hz": 360
		},
		{
			"user": "Joshua83",
			"link": "https://youtu.be/sb1QtQ5vCIw",
			"percent": 100,
			"hz": 360
		},
		{
			"user": "Hubertos",
			"link": "https://youtu.be/rAmreDpd3pU",
			"percent": 100,
			"hz": 360
		},
		{
			"user": "PurpleAnchor",
			"link": "https://www.youtube.com/watch?v=BH3ejFqqITk&t=5s",
			"percent": 100,
			"hz": 360
		},
		{
			"user": "[MOAT] Popsi",
			"link": "https://www.youtube.com/watch?v=8L2UoI05oz8",
			"percent": 100,
			"hz": 360
		},
		{
			"user": "StarXV",
			"link": "https://youtu.be/SUSyTCCpAgI",
			"percent": 100,
			"hz": 360
		},
		{
			"user": "asdsdvb",
			"link": "https://www.youtube.com/watch?v=BRvW6p-MInM",
			"percent": 100,
			"hz": 360
		},
		{
			"user": "Reffman",
			"link": "https://youtu.be/7pCCe9W1-a0",
			"percent": 100,
			"hz": 360
		},
		{
			"user": "Bruno27YT",
			"link": "https://youtu.be/19lVdnToDno?si=pzJK5_V33dFad0iD",
			"percent": 100,
			"hz": 360
		},
		{
			"user": "nacho31",
			"link": "https://youtu.be/Di1-1EVfSWI?si=55oJVOm0omAbV1s_",
			"percent": 100,
			"hz": 360,
			"mobile": true
		}
	]
}