{
	"id": 108963146,
	"name": "OUTPUT SPRING",
	"author": "TheRealXFuture",
	"creators": [],
	"verifier": "Sync Jaws",
	"verification": "https://www.youtube.com/watch?v=iKrad6rQyLA&t=0s",
	"percentToQualify": 100,
	"password": "No Copy",
	"records": [
		{
			"user": "Oblivionus",
			"link": "https://youtu.be/rNbu0AStNm4",
			"percent": 100,
			"hz": 360
		},
		{
			"user": "exerity",
			"link": "https://youtu.be/IR5N_TfWB7Y?si=eVBLyuc2dLrf0ETA",
			"percent": 100,
			"hz": 360
		},
		{
			"user": "DimanDash",
			"link": "https://youtu.be/5AR-vQaElC0",
			"percent": 100,
			"hz": 360
		}
	]
}