{
    "id": 78470229,
    "name": "Shitty Prismatic Haze",
    "author": "zPhysixX",
    "creators": [],
    "verifier": "Davine_007",
    "verification": "https://youtu.be/QUdN2asWQeo",
    "percentToQualify": 64,
    "records": [
        {
            "user": "ZerniasX",
            "link": "https://youtu.be/9iir2ZiyDMo",
            "percent": 100,
            "hz": 360
        },
        {
            "user": "Chr8ts",
            "link": "https://youtu.be/7TudQaXUqJM",
            "percent": 100,
            "hz": 240
        },
        {
            "user": "Emonadeo",
            "link": "https://www.youtube.com/watch?v=H6oI7ielyzA",
            "percent": 100,
            "hz": 240
        },
        {
            "user": "Riptide",
            "link": "https://youtu.be/f5UJKyLu23Q",
            "percent": 100,
            "hz": 120
        },
        {
            "user": "Decin0",
            "link": "https://youtu.be/eaN7cx1rBKU",
            "percent": 100,
            "hz": 288
        },
        {
            "user": "Korvak",
            "link": "https://www.youtube.com/watch?v=aMPid8HIECw",
            "percent": 100,
            "hz": 288
        },
        {
            "user": "T333",
            "link": "https://youtu.be/GqYhu9VJ74c",
            "percent": 100,
            "hz": 240
        },
        {
            "user": "Andrxw",
            "link": "https://www.youtube.com/watch?v=1En9exZ-FK4",
            "percent": 100,
            "hz": 144
        },
        {
            "user": "Xarii_72",
            "link": "https://youtu.be/aUINpciCtF8",
            "percent": 100,
            "hz": 240
        },
        {
            "user": "Hasik",
            "link": "https://youtu.be/SgmJvq6JY4g",
            "percent": 100,
            "hz": 165
        },
        {
            "user": "Invinceicube",
            "link": "https://youtu.be/GbBG7qyTBr4",
            "percent": 100,
            "hz": 240
        },
        {
            "user": "BliffY",
            "link": "https://www.youtube.com/watch?v=xcIFXt9De74",
            "percent": 100,
            "hz": 360
        },
        {
            "user": "NanCho",
            "link": "https://youtu.be/PVKjnSAzlDg",
            "percent": 100,
            "hz": 360
        },
        {
            "user": "BlueTomcat",
            "link": "https://youtu.be/A0Xk6dJoQ_M",
            "percent": 100,
            "hz": 288
        },
        {
            "user": "Shemenzy",
            "link": "https://www.youtube.com/watch?v=g-IMyopgTMY",
            "percent": 100,
            "hz": 300
        },
        {
            "user": "attrixia",
            "link": "https://www.youtube.com/watch?v=to5ryuc_F94",
            "percent": 100,
            "hz": 150
        },
        {
            "user": "He_rules",
            "link": "https://www.youtube.com/watch?v=3jLg0FVhhsI",
            "percent": 100,
            "hz": 144
        },
        {
            "user": "YinnYang",
            "link": "https://youtu.be/JH-wa4NqzlU",
            "percent": 100,
            "hz": 360
        },
        {
            "user": "Tango",
            "link": "https://www.youtube.com/watch?v=-VbPMGNa8hw",
            "percent": 100,
            "hz": 144
        },
        {
            "user": "Hoopla",
            "link": "https://youtu.be/t4rU90_U1ew",
            "percent": 100,
            "hz": 360
        },
        {
            "user": "TurtleER",
            "link": "https://www.youtube.com/watch?v=lJnmy6QVT40&ab_channel=TurtleERClips",
            "percent": 100,
            "hz": 240
        },
        {
            "user": "oBynxi",
            "link": "https://www.youtube.com/watch?v=guLsKcZRvpI",
            "percent": 100,
            "hz": 240
        },
        {
            "user": "GlitchyGlotch",
            "link": "https://youtu.be/1_A3861vSVg",
            "percent": 100,
            "hz": 360
        },
        {
            "user": "lucap123",
            "link": "https://www.youtube.com/watch?v=1N8SUY2uDTY",
            "percent": 100,
            "hz": 144
        },
        {
            "user": "TkcpeR",
            "link": "https://youtu.be/-suW20k0UEw",
            "percent": 100,
            "hz": 360
        }
    ]
}
