{
	"id": 81372683,
	"name": "RANDOM ACCESS MEMORY",
	"tags": [
		"2.1",
		"Long",
		"Learny",
		"Memory",
		"High CPS",
		"Timings",
		"Duals",
		"Chokepoints"
	],
	"author": 5128223367,
	"creators": [
		5050645637,
		3667521619,
		5312127109,
		5770224265,
		7963287990,
		4051969182,
		3072077927,
		2392099922,
		5128223367,
		1660851943
	],
	"verifier": 5312127109,
	"verification": "https://www.youtube.com/watch?v=6_pYfJKKpRY",
	"percentToQualify": 100,
	"password": "471206",
	"song": 1068608,
	"records": [
		{
			"user": 3525146362,
			"link": "https://youtu.be/2KxVrOrGBN0",
			"percent": 100,
			"hz": 360
		},
		{
			"user": 3362805527,
			"link": "https://youtu.be/18nLNKhKtow",
			"percent": 100,
			"hz": 360
		},
		{
			"user": 3261273833,
			"link": "https://www.youtube.com/watch?v=G7EtSlAI_zo",
			"percent": 100,
			"hz": 144
		},
		{
			"user": 3050190027,
			"link": "https://youtu.be/_b0lO4BfO10",
			"percent": 100,
			"hz": 240
		},
		{
			"user": 9586710551,
			"link": "https://youtu.be/bv23UDUjfgY",
			"percent": 100,
			"hz": 360
		},
		{
			"user": 7403208507,
			"link": "https://youtu.be/EaRYyJd-wXw",
			"percent": 100,
			"hz": 240
		},
		{
			"user": 5757119686,
			"link": "https://youtu.be/2F3rYuzhyYA",
			"percent": 100,
			"hz": 360
		},
		{
			"user": 8512044810,
			"link": "https://www.youtube.com/watch?v=ddbaojfLIIM",
			"percent": 100,
			"hz": 144
		},
		{
			"user": 3950482202,
			"link": "https://www.youtube.com/watch?v=QHj3Ma_cRVE",
			"percent": 100,
			"hz": 360
		},
		{
			"user": 9349980438,
			"link": "https://www.youtube.com/watch?v=qUKpiZvSZKA",
			"percent": 100,
			"hz": 360
		},
		{
			"user": 9561396744,
			"link": "https://youtu.be/b5wj9CnGkTk",
			"percent": 100,
			"hz": 240
		},
		{
			"user": 6807948992,
			"link": "https://www.youtube.com/watch?v=bBqwvdGzIfY",
			"percent": 100,
			"hz": 240
		},
		{
			"user": 4886572813,
			"link": "https://youtu.be/l9tO1o1QI0g",
			"percent": 100,
			"hz": 360
		},
		{
			"user": 8563786231,
			"link": "https://youtu.be/RBhIBOCTomo",
			"percent": 100,
			"hz": 360
		},
		{
			"user": 9879633307,
			"link": "https://youtu.be/IH0E16WEuJ8?si=sJYqWvE5VJ2X47LO",
			"percent": 100,
			"hz": 360
		},
		{
			"user": 4225547747,
			"link": "https://www.youtube.com/watch?v=z3hZSYEtF_4&t=141s",
			"percent": 100,
			"hz": 360
		},
		{
			"user": 3377410347,
			"link": "https://youtu.be/SEsZABF5fRY?si=wMOfXsZz2jmnv2R7",
			"percent": 100,
			"hz": 360
		},
		{
			"user": 2250290720,
			"link": "https://youtu.be/AFxn3ZL3Qzw?si=VayGkkFAmhYGSTdU",
			"percent": 100,
			"hz": 360
		},
		{
			"user": 3969992072,
			"link": "https://youtu.be/ij6x9wmpFT0",
			"percent": 100,
			"hz": 360
		},
		{
			"user": 6067575057,
			"link": "https://youtu.be/4jBMC88Rc8Q?si=rTzNhsy6kc9T7mh4",
			"percent": 100,
			"hz": 360
		},
		{
			"user": 7937190301,
			"link": "https://www.youtube.com/watch?v=c0f10APxA-4",
			"percent": 100,
			"hz": 360
		},
		{
			"user": 3442731355,
			"link": "https://youtu.be/MpyHv5cUA_o",
			"percent": 100,
			"hz": 360
		}
	]
}