{
	"id": 114933189,
	"name": "Through The Decay",
	"tags": [
		"2.2",
		"Long",
		"Timings",
		"Slow-Paced"
	],
	"author": 7631599083,
	"creators": [
		7631599083
	],
	"verifier": 7631599083,
	"verification": "https://youtu.be/djPTTc2vTd4?si=gDkLiiqdJR_VF1mm",
	"percentToQualify": 100,
	"password": "Free Copy",
	"records": [
		{
			"user": 6679096678,
			"link": "https://youtu.be/HEK5q0SlyWg?si=zjGKdIDzv_A0IOsi",
			"percent": 100,
			"hz": 360
		},
		{
			"user": 4693616315,
			"link": "https://www.youtube.com/live/RJUs-8Ik7Og",
			"percent": 100,
			"hz": 360
		},
		{
			"user": 4007883613,
			"link": "https://www.youtube.com/watch?v=VKSXxqS95XM",
			"percent": 100,
			"hz": 360
		},
		{
			"user": 9309848890,
			"link": "https://youtu.be/bvAI91AHLvk?si=NWhclsunMM86_076",
			"percent": 100,
			"hz": 360
		},
		{
			"user": 2642417745,
			"link": "https://youtu.be/hEzVWrDNBr8?si=N2r7wjXA1JS8LWbk",
			"percent": 100,
			"hz": 360
		},
		{
			"user": 3904474001,
			"link": "https://youtu.be/J48-0LPUjoA?si=uzKY28DNgCBzUfpS",
			"percent": 100,
			"hz": 360
		},
		{
			"user": 1520491601,
			"link": "https://youtu.be/r-KSdckiFbw",
			"percent": 100,
			"hz": 360
		},
		{
			"user": 1870674826,
			"link": "https://www.youtube.com/watch?v=B_QXeFSeymw",
			"percent": 100,
			"hz": 360
		},
		{
			"user": 8568721165,
			"link": "https://youtu.be/JVqejWLBuCQ",
			"percent": 100,
			"hz": 360
		},
		{
			"user": 5997638100,
			"link": "https://www.youtube.com/watch?v=807NBdbFUYU",
			"percent": 100,
			"hz": 360
		},
		{
			"user": 2628372200,
			"link": "https://www.youtube.com/watch?v=wbbvIe0c1LU",
			"percent": 100,
			"hz": 360
		},
		{
			"user": 2908765776,
			"link": "https://youtu.be/dCYa6b75a0c",
			"percent": 100,
			"hz": 360
		},
		{
			"user": 2674551082,
			"link": "https://www.youtube.com/watch?v=hocY0SdTVSI",
			"percent": 100,
			"hz": 360
		},
		{
			"user": 9334359459,
			"link": "https://www.tiktok.com/@duckngl/video/7475875360328944927?is_from_webapp=1&sender_device=pc&web_id=7265110287506261547",
			"percent": 100,
			"hz": 360
		},
		{
			"user": 6618100123,
			"link": "https://youtu.be/ArFyXeHnr40?si=cXOmr91OKDzVmBVB",
			"percent": 100,
			"hz": 360
		},
		{
			"user": 8411935000,
			"link": "https://www.youtube.com/watch?v=fOPc3WZFmLI",
			"percent": 100,
			"hz": 360
		},
		{
			"user": 1303264773,
			"link": "https://youtu.be/6pPUxiza2ik?si=mMMHb8EfZ_TfyK9C",
			"percent": 100,
			"hz": 360
		},
		{
			"user": 6075205327,
			"link": "https://youtu.be/3uKRLL23aWU?si=9fK56GEyxr2iQBtY",
			"percent": 100,
			"hz": 360
		},
		{
			"user": 7480943157,
			"link": "https://youtu.be/aDixjS6z270",
			"percent": 100,
			"hz": 360
		},
		{
			"user": 1026739108,
			"link": "https://www.youtube.com/watch?v=vAIDkiDfgaA",
			"percent": 100,
			"hz": 360
		},
		{
			"user": 8897977647,
			"link": "https://www.youtube.com/watch?v=0rL0JDhLJNo",
			"percent": 100,
			"hz": 360
		},
		{
			"user": 1069746988,
			"link": "https://youtu.be/CPz-cEx610g",
			"percent": 100,
			"hz": 360
		},
		{
			"user": 9835771025,
			"link": "https://youtu.be/43yvm8Lxf00",
			"percent": 100,
			"hz": 360
		},
		{
			"user": 8090506723,
			"link": "https://drive.google.com/file/d/1ZShJ4NZTJ0uFTKLzc32kLmQNVDoUQ98u/view?usp=sharing",
			"percent": 100,
			"hz": 360
		},
		{
			"user": 8919887616,
			"link": "https://youtu.be/Yp6v8WDPJuI?si=UeZGnnjUF8s9GdZI",
			"percent": 100,
			"hz": 360
		},
		{
			"user": 5553813223,
			"link": "https://youtu.be/-_ejhi7vDOk",
			"percent": 100,
			"hz": 360
		},
		{
			"user": 4184571314,
			"link": "https://youtu.be/vdsehGx-3Ms?si=AUVo9G-4SXylqoHL",
			"percent": 100,
			"hz": 360
		},
		{
			"user": 6960007777,
			"link": "https://youtu.be/34qaNBrgYao",
			"percent": 100,
			"hz": 360
		},
		{
			"user": 2414291216,
			"link": "https://youtu.be/ZZBlmWoBSmI",
			"percent": 100,
			"hz": 360
		},
		{
			"user": 9246230842,
			"link": "https://youtu.be/4UfQxQrQVHI",
			"percent": 100,
			"hz": 360
		},
		{
			"user": 8523832608,
			"link": "https://youtu.be/3aw_oDQD0Ag",
			"percent": 100,
			"hz": 360
		},
		{
			"user": 5757119686,
			"link": "https://youtu.be/zGw_zrlFGys",
			"percent": 100,
			"hz": 360
		},
		{
			"user": 2464754572,
			"link": "https://www.youtube.com/watch?v=NTjvkFLG9ug&t=28s",
			"percent": 100,
			"hz": 360
		},
		{
			"user": 8290982750,
			"link": "https://www.youtube.com/watch?v=-oSil59hm_g",
			"percent": 100,
			"hz": 360
		},
		{
			"user": 7331741353,
			"link": "https://youtu.be/CKiVBKf0lDQ?si=Ph3UhgSRfsqoHJ3y",
			"percent": 100,
			"hz": 360,
			"mobile": true
		},
		{
			"user": 7286417697,
			"link": "https://youtu.be/1u55rmZcdTA",
			"percent": 100,
			"hz": 360
		},
		{
			"user": 5050254293,
			"link": "https://youtu.be/iRR8tJKYSO0?si=AOIy4C8XCZnd0bBu",
			"percent": 100,
			"hz": 360
		},
		{
			"user": 4472490897,
			"link": "https://youtu.be/dg_GNFgIxyo",
			"percent": 100,
			"hz": 360
		},
		{
			"user": 1442071037,
			"link": "https://www.youtube.com/watch?v=6MfJpNhb9OM",
			"percent": 100,
			"hz": 360
		},
		{
			"user": 3724410559,
			"link": "https://www.youtube.com/watch?v=NqU7KkHv2PU&t=5s&ab_channel=Mel",
			"percent": 100,
			"hz": 360
		},
		{
			"user": 4758086202,
			"link": "https://youtu.be/_cAlRy9R0g0",
			"percent": 100,
			"hz": 360
		},
		{
			"user": 4157625283,
			"link": "https://medal.tv/games/geometry-dash/clips/jSfLqkgTvyuBqZwYd?invite=cr-MSxXbnAsMjAzOTQzOTI1LA",
			"percent": 100,
			"hz": 360
		},
		{
			"user": 5164016369,
			"link": "https://www.youtube.com/watch?v=tFqL4RHHq_4",
			"percent": 100,
			"hz": 360
		},
		{
			"user": 5595225732,
			"link": "https://www.youtube.com/watch?v=O7OSBpYu6ko",
			"percent": 100,
			"hz": 360
		},
		{
			"user": 9816161216,
			"link": "https://youtu.be/1qpcFcwdAzg",
			"percent": 100,
			"hz": 360
		},
		{
			"user": 9320704479,
			"link": "https://youtu.be/8NQdG6v2GDM",
			"percent": 100,
			"hz": 360
		},
		{
			"user": 1492178495,
			"link": "https://www.youtube.com/watch?v=hPx5ofW_EWg",
			"percent": 100,
			"hz": 360
		},
		{
			"user": 3740620269,
			"link": "https://youtu.be/xjWD-yTiyCo",
			"percent": 100,
			"hz": 360
		},
		{
			"user": 9700403968,
			"link": "https://youtu.be/N-YbaJzkEqE",
			"percent": 100,
			"hz": 360
		},
		{
			"user": 3981630040,
			"link": "https://youtu.be/KRMB2PT7JV0",
			"percent": 100,
			"hz": 360
		},
		{
			"user": 8416165965,
			"link": "https://youtu.be/iP8_sgjXYbE",
			"percent": 100,
			"hz": 360
		},
		{
			"user": 7878610721,
			"link": "https://youtu.be/f48TpGoYL7Q",
			"percent": 100,
			"hz": 360
		},
		{
			"user": 7843071234,
			"link": "https://youtu.be/k2lMeLsVqZ0?si=0oqaZQx1orl6H5zu",
			"percent": 100,
			"hz": 360
		},
		{
			"user": 2098744186,
			"link": "https://youtu.be/S2_tHtImPbQ?si=Asl7g2sLUUcelULN",
			"percent": 100,
			"hz": 360
		},
		{
			"user": 8904205120,
			"link": "https://youtu.be/rsyN54gBc-g?si=nRcZqjn3yHWf4o5V",
			"percent": 100,
			"hz": 360
		},
		{
			"user": 8163564178,
			"link": "https://www.youtube.com/watch?v=J7oQ6PdVpjc",
			"percent": 100,
			"hz": 360
		},
		{
			"user": 6333544869,
			"link": "https://youtu.be/9rAMgAgBF0g",
			"percent": 100,
			"hz": 360
		},
		{
			"user": 4095503736,
			"link": "https://youtu.be/ivAhlG81lG0?si=NqfmPsM4Wkgpg_I0",
			"percent": 100,
			"hz": 360,
			"mobile": true
		},
		{
			"user": 9004294264,
			"link": "https://youtu.be/b-OKdygROyA",
			"percent": 100,
			"hz": 360
		},
		{
			"user": 9998499720,
			"link": "https://www.youtube.com/watch?v=9w34-VJMJWM",
			"percent": 100,
			"hz": 360
		},
		{
			"user": 1752396906,
			"link": "https://youtu.be/CYJ-P8w2OxA",
			"percent": 100,
			"hz": 360
		},
		{
			"user": 4005994202,
			"link": "https://www.youtube.com/watch?v=5H_Vne1iYZg",
			"percent": 100,
			"hz": 360
		},
		{
			"user": 7678386617,
			"link": "https://www.youtube.com/watch?v=KYkTzGDwEhs",
			"percent": 100,
			"hz": 360
		},
		{
			"user": 9519787906,
			"link": "https://youtu.be/hVVO1UpUbvk",
			"percent": 100,
			"hz": 360
		},
		{
			"user": 2335300508,
			"link": "https://youtu.be/P5yesFIEuKY?si=lNP6VBWkA47PUAeZ",
			"percent": 100,
			"hz": 360
		},
		{
			"user": 5031131671,
			"link": "https://youtu.be/L_iTdiY_r40",
			"percent": 100,
			"hz": 360
		},
		{
			"user": 4312662139,
			"link": "https://www.youtube.com/watch?v=kjhQrrTICmQ",
			"percent": 100,
			"hz": 360
		},
		{
			"user": 4394743141,
			"link": "https://youtu.be/frXk7heKU5g",
			"percent": 100,
			"hz": 360
		},
		{
			"user": 3366545273,
			"link": "https://youtu.be/eh4hPJQZ4bs",
			"percent": 100,
			"hz": 360
		},
		{
			"user": 7234063377,
			"link": "https://youtu.be/nqTok7oyoNc",
			"percent": 100,
			"hz": 360
		},
		{
			"user": 1951133750,
			"link": "https://youtu.be/X2xbVIEsrsc",
			"percent": 100,
			"hz": 360
		},
		{
			"user": 5742664742,
			"link": "https://www.youtube.com/watch?v=VKzOaHdyyts",
			"percent": 100,
			"hz": 360
		},
		{
			"user": 4316700639,
			"link": "https://www.youtube.com/watch?v=v36zYTb9Yyc",
			"percent": 100,
			"hz": 360
		},
		{
			"user": 7949774184,
			"link": "https://youtu.be/qdicdZoUOeU",
			"percent": 100,
			"hz": 360
		},
		{
			"user": 3546655182,
			"link": "https://www.youtube.com/watch?v=iZvBKBB3bzI",
			"percent": 100,
			"hz": 360
		},
		{
			"user": 4704035130,
			"link": "https://youtu.be/lE54KSs53M8",
			"percent": 100,
			"hz": 360
		},
		{
			"user": 1552473546,
			"link": "https://youtu.be/3vNr837S0y4?si=JyZiysKsW3BfwUA-",
			"percent": 100,
			"hz": 360
		},
		{
			"user": 5959115732,
			"link": "https://youtu.be/V4HDM2TyBDM",
			"percent": 100,
			"hz": 360
		},
		{
			"user": 3389316637,
			"link": "https://youtu.be/NqBmsF19zTQ?si=iWOWr6E-O3iBqpmd",
			"percent": 100,
			"hz": 360
		},
		{
			"user": 2546534249,
			"link": "https://www.youtube.com/watch?v=wADCR91k7fg",
			"percent": 100,
			"hz": 360
		},
		{
			"user": 6924001310,
			"link": "https://youtu.be/1iZHfmjJhcc",
			"percent": 100,
			"hz": 360
		},
		{
			"user": 4502219941,
			"link": "https://youtu.be/Rxoti4aVUg0",
			"percent": 100,
			"hz": 360
		},
		{
			"user": 5908120379,
			"link": "https://youtu.be/eTC0eoE3xCI?si=oKwqjNB1-U79hGz-",
			"percent": 100,
			"hz": 360
		},
		{
			"user": 5067954587,
			"link": "https://youtu.be/qqjFTuViUlQ",
			"percent": 100,
			"hz": 360
		},
		{
			"user": 3969992072,
			"link": "https://www.youtube.com/watch?v=TG6J355CR10&ab_channel=derf",
			"percent": 100,
			"hz": 360
		},
		{
			"user": 4886572813,
			"link": "https://youtu.be/-fA-JiGGP4c",
			"percent": 100,
			"hz": 360
		},
		{
			"user": 8181101088,
			"link": "https://youtu.be/ONLWoNueh9M?si=fkCLwy0udRSIawud",
			"percent": 100,
			"hz": 360
		},
		{
			"user": 6320631807,
			"link": "https://youtu.be/e8Y5R6H1Ge0?si=-r0Krrl2Mm6HKtgW",
			"percent": 100,
			"hz": 360
		},
		{
			"user": 3650599042,
			"link": "https://www.youtube.com/watch?v=du4h85XMUJY",
			"percent": 100,
			"hz": 360
		},
		{
			"user": 4196126169,
			"link": "https://youtu.be/nH2d8fZMeEc?feature=shared",
			"percent": 100,
			"hz": 360
		},
		{
			"user": 4757349998,
			"link": "https://youtu.be/Yf92_-RxmA0",
			"percent": 100,
			"hz": 360
		},
		{
			"user": 1877340554,
			"link": "https://youtu.be/z4z7MhdINmY?si=2t0m7IkLjTshvf4S",
			"percent": 100,
			"hz": 360
		},
		{
			"user": 8817965175,
			"link": "https://youtu.be/rEh73FQi1vs?si=9bLM5VlrPt7xa91w",
			"percent": 100,
			"hz": 360
		},
		{
			"user": 3708652205,
			"link": "https://www.youtube.com/watch?v=IaUMCbLfsfM",
			"percent": 100,
			"hz": 360
		},
		{
			"user": 1109995755,
			"link": "https://www.youtube.com/watch?v=bJTKnxSLG1Q",
			"percent": 100,
			"hz": 360
		},
		{
			"user": 3393474485,
			"link": "https://youtu.be/5xrjV0qdqFo?si=PyxVgVZHuhwyVCoo",
			"percent": 100,
			"hz": 360
		},
		{
			"user": 8418250109,
			"link": "https://youtu.be/TMyPKJpDkRM?si=hAotkIl826Cg7-Sz",
			"percent": 100,
			"hz": 360
		},
		{
			"user": 7928488134,
			"link": "https://youtu.be/siJx1SrCHDo",
			"percent": 100,
			"hz": 360
		},
		{
			"user": 1154410679,
			"link": "https://youtu.be/b2wKf34unsA",
			"percent": 100,
			"hz": 360
		},
		{
			"user": 6875888497,
			"link": "https://www.youtube.com/watch?v=P0bPBV2sbuo&t=11s",
			"percent": 100,
			"hz": 360
		},
		{
			"user": 4824398482,
			"link": "https://youtu.be/1yu9JqcqOVY?si=8M0QWtp44DsxThSh",
			"percent": 100,
			"hz": 360,
			"mobile": true
		},
		{
			"user": 5556353600,
			"link": "https://youtu.be/DYZ6Di-J-uo?si=_Mtxwa9q2_AcEcaB",
			"percent": 100,
			"hz": 360
		},
		{
			"user": 2406725063,
			"link": "https://youtu.be/_YSMk_pyHKg?si=Tn6R5aO9rPF0rCiD",
			"percent": 100,
			"hz": 360
		},
		{
			"user": 8521393922,
			"link": "https://www.youtube.com/watch?v=vRZVxuA0xE8&lc=UgyYTtT6wm4SEff_osJ4AaABAg",
			"percent": 100,
			"hz": 360
		},
		{
			"user": 8822751861,
			"link": "https://www.youtube.com/watch?v=dPQfIaPX1nQ",
			"percent": 100,
			"hz": 360
		},
		{
			"user": 4569566869,
			"link": "https://youtu.be/HZ77cQrrqZM",
			"percent": 100,
			"hz": 360
		},
		{
			"user": 4428009011,
			"link": "https://youtu.be/zSxsTYvnuwk",
			"percent": 100,
			"hz": 360
		},
		{
			"user": 1751809723,
			"link": "https://www.youtube.com/watch?v=azPxN-JgXwE",
			"percent": 100,
			"hz": 360
		},
		{
			"user": 2067487205,
			"link": "https://youtu.be/eHlYtsYKfw0",
			"percent": 100,
			"hz": 360
		},
		{
			"user": 7931097194,
			"link": "https://youtu.be/XihBosvEo2c?si=G-sL2DQA24atV-t6",
			"percent": 100,
			"hz": 360
		},
		{
			"user": 7068681694,
			"link": "https://youtu.be/jNjSJ2qNBG4?si=xnFgZGGOKwVY6IQb",
			"percent": 100,
			"hz": 360
		},
		{
			"user": 3844655556,
			"link": "https://www.youtube.com/watch?v=9ZdiSkEJhHc&list=PLlDJL9hpn9kPLe_Rpq8qbfrhHXKZX8ybf",
			"percent": 100,
			"hz": 360
		},
		{
			"user": 7760886599,
			"link": "https://youtu.be/uutfUcXxxhg?si=KdTZV4Jj_2lQMz9V",
			"percent": 100,
			"hz": 360
		},
		{
			"user": 7268700769,
			"link": "https://youtu.be/or1ofki3O6Y",
			"percent": 100,
			"hz": 360
		},
		{
			"user": 1669862445,
			"link": "https://youtu.be/qq--2OAE9uQ",
			"percent": 100,
			"hz": 360
		},
		{
			"user": 6722128398,
			"link": "https://www.youtube.com/watch?v=BBcL9CU0oeA",
			"percent": 100,
			"hz": 360
		},
		{
			"user": 4317638521,
			"link": "https://youtu.be/UaY5pqUOUjc",
			"percent": 100,
			"hz": 360
		},
		{
			"user": 8760796734,
			"link": "https://www.youtube.com/watch?v=vYWZ-xuzBUM",
			"percent": 100,
			"hz": 360
		},
		{
			"user": 4608947309,
			"link": "https://youtu.be/eU-hgZGcH-g",
			"percent": 100,
			"hz": 360
		},
		{
			"user": 6364793048,
			"link": "https://www.youtube.com/watch?v=2N4EPWVNyAM",
			"percent": 100,
			"hz": 360
		},
		{
			"user": 2893228039,
			"link": "https://youtu.be/jb115Ex1gNc",
			"percent": 100,
			"hz": 360
		},
		{
			"user": 5178016523,
			"link": "https://www.youtube.com/watch?v=7YqBztSyo9M",
			"percent": 100,
			"hz": 360
		},
		{
			"user": 1769105544,
			"link": "https://youtu.be/Gja5826GxEc",
			"percent": 100,
			"hz": 360
		},
		{
			"user": 9230723024,
			"link": "https://www.youtube.com/watch?v=sb6WruBnp8s",
			"percent": 100,
			"hz": 360
		},
		{
			"user": 2929459386,
			"link": "https://youtu.be/o1I5zaZJyoU?si=E-3xldeFNcEwIy7C",
			"percent": 100,
			"hz": 360
		},
		{
			"user": 6097447596,
			"link": "https://www.youtube.com/watch?v=TDS7QFRL0bs&ab_channel=GabriNick",
			"percent": 100,
			"hz": 360
		},
		{
			"user": 8494923085,
			"link": "https://youtu.be/1gS77f54Ej8",
			"percent": 100,
			"hz": 360
		},
		{
			"user": 6678085735,
			"link": "https://youtu.be/vpuJa3t70iY",
			"percent": 100,
			"hz": 360
		},
		{
			"user": 4531491759,
			"link": "https://youtu.be/z4Q2f-PsFv4",
			"percent": 100,
			"hz": 360
		},
		{
			"user": 6721491796,
			"link": "https://youtu.be/v1R-0r2AylQ",
			"percent": 100,
			"hz": 360
		},
		{
			"user": 9041327075,
			"link": "https://www.youtube.com/watch?v=BJ-RemP59qI",
			"percent": 100,
			"hz": 360
		}
	]
}